mcp_server/__init__.py
mcp_server/server.py
mcp_server/entities/flow.py
mcp_server/entities/ifly_client.py
mseep_ifly_workflow_mcp_server-1.0.2.dist-info/METADATA
mseep_ifly_workflow_mcp_server-1.0.2.dist-info/WHEEL
mseep_ifly_workflow_mcp_server-1.0.2.dist-info/entry_points.txt
mseep_ifly_workflow_mcp_server-1.0.2.dist-info/licenses/LICENSE
mseep_ifly_workflow_mcp_server-1.0.2.dist-info/RECORD
